{"assets":{"C315C0CED7395291870A6BBEA0409089":{"type":"texture","index":13,"assetRequest":{"type":"slide","state":"incoming","slide":"68183ACD-66C9-4234-8543-82B4979C9ACD"},"url":"assets/C315C0CED7395291870A6BBEA0409089.svg","width":640,"height":1136},"2FCE521D6A14D1F4D863CA0218998B63":{"type":"texture","index":12,"assetRequest":{"type":"slide","state":"incoming","slide":"476578B4-8979-4D0A-9BA5-CF3157675D5D"},"url":"assets/2FCE521D6A14D1F4D863CA0218998B63.png","width":640,"height":1136},"AAF1CC47F60B5C2D43150347C2A117E5":{"type":"texture","index":11,"assetRequest":{"type":"slide","state":"outgoing","slide":"211BC1BC-EA43-4F7B-BDD6-52AE52CC28A7"},"url":"assets/AAF1CC47F60B5C2D43150347C2A117E5.png","width":640,"height":1136}},"events":[{"effects":[{"beginTime":0,"baseLayer":{"animations":[],"initialState":{"affineTransform":[1,0,0,1,0,0],"masksToBounds":true,"rotation":0,"scale":1,"position":{"pointX":320,"pointY":568},"width":640,"sublayerTransform":[1,0,0,0,0,1,0,0,0,0,1,0,0,0,0,1],"contentsRect":{"y":0,"x":0,"width":1,"height":1},"opacity":1,"edgeAntialiasingMask":0,"height":1136,"hidden":false,"anchorPoint":{"pointX":0.5,"pointY":0.5}},"objectID":"0","layers":[{"animations":[],"initialState":{"affineTransform":[1,0,0,1,0,0],"masksToBounds":false,"rotation":0,"scale":1,"position":{"pointX":320,"pointY":568},"width":640,"sublayerTransform":[1,0,0,0,0,1,0,0,0,0,1,-0.0005907585228768447,0,0,0,1],"contentsRect":{"y":0,"x":0,"width":1,"height":1},"opacity":1,"edgeAntialiasingMask":15,"height":1136,"hidden":false,"anchorPoint":{"pointX":0.5,"pointY":0.5}},"layers":[{"animations":[],"layers":[],"initialState":{"affineTransform":[1,0,0,1,0,0],"masksToBounds":false,"rotation":0,"scale":1,"position":{"pointX":320,"pointY":568},"width":640,"sublayerTransform":[1,0,0,0,0,1,0,0,0,0,1,0,0,0,0,1],"contentsRect":{"y":0,"x":0,"width":1,"height":1},"opacity":1,"edgeAntialiasingMask":0,"height":1136,"hidden":false,"anchorPoint":{"pointX":0.5,"pointY":0.5}},"texture":"2FCE521D6A14D1F4D863CA0218998B63"},{"animations":[{"from":{"scalar":false},"beginTime":0,"repeatCount":0,"fillMode":"both","property":"hidden","duration":0.01,"to":{"scalar":true}}],"layers":[],"initialState":{"affineTransform":[1,0,0,1,0,0],"masksToBounds":false,"rotation":0,"scale":1,"position":{"pointX":320,"pointY":568},"width":640,"sublayerTransform":[1,0,0,0,0,1,0,0,0,0,1,0,0,0,0,1],"contentsRect":{"y":0,"x":0,"width":1,"height":1},"opacity":1,"edgeAntialiasingMask":0,"height":1136,"hidden":false,"anchorPoint":{"pointX":0.5,"pointY":0.5}},"texture":"AAF1CC47F60B5C2D43150347C2A117E5"}]}]},"effects":[],"duration":0.01,"type":"transition","name":"none","objectID":"0"}],"automaticPlay":false,"hyperlinks":[{"url":"?slideid=68183ACD-66C9-4234-8543-82B4979C9ACD","events":{"68183ACD-66C9-4234-8543-82B4979C9ACD":{"effects":[{"beginTime":0,"baseLayer":{"animations":[],"initialState":{"affineTransform":[1,0,0,1,0,0],"masksToBounds":true,"rotation":0,"scale":1,"position":{"pointX":320,"pointY":568},"width":640,"sublayerTransform":[1,0,0,0,0,1,0,0,0,0,1,0,0,0,0,1],"contentsRect":{"y":0,"x":0,"width":1,"height":1},"opacity":1,"edgeAntialiasingMask":0,"height":1136,"hidden":false,"anchorPoint":{"pointX":0.5,"pointY":0.5}},"objectID":"0","layers":[{"animations":[],"initialState":{"affineTransform":[1,0,0,1,0,0],"masksToBounds":false,"rotation":0,"scale":1,"position":{"pointX":320,"pointY":568},"width":640,"sublayerTransform":[1,0,0,0,0,1,0,0,0,0,1,-0.0005907585228768447,0,0,0,1],"contentsRect":{"y":0,"x":0,"width":1,"height":1},"opacity":1,"edgeAntialiasingMask":15,"height":1136,"hidden":false,"anchorPoint":{"pointX":0.5,"pointY":0.5}},"layers":[{"animations":[],"layers":[],"initialState":{"affineTransform":[1,0,0,1,0,0],"masksToBounds":false,"rotation":0,"scale":1,"position":{"pointX":320,"pointY":568},"width":640,"sublayerTransform":[1,0,0,0,0,1,0,0,0,0,1,0,0,0,0,1],"contentsRect":{"y":0,"x":0,"width":1,"height":1},"opacity":1,"edgeAntialiasingMask":0,"height":1136,"hidden":false,"anchorPoint":{"pointX":0.5,"pointY":0.5}},"texture":"C315C0CED7395291870A6BBEA0409089"},{"animations":[{"from":{"scalar":false},"beginTime":0,"repeatCount":0,"fillMode":"both","property":"hidden","duration":0.01,"to":{"scalar":true}}],"layers":[],"initialState":{"affineTransform":[1,0,0,1,0,0],"masksToBounds":false,"rotation":0,"scale":1,"position":{"pointX":320,"pointY":568},"width":640,"sublayerTransform":[1,0,0,0,0,1,0,0,0,0,1,0,0,0,0,1],"contentsRect":{"y":0,"x":0,"width":1,"height":1},"opacity":1,"edgeAntialiasingMask":0,"height":1136,"hidden":false,"anchorPoint":{"pointX":0.5,"pointY":0.5}},"texture":"AAF1CC47F60B5C2D43150347C2A117E5"}]}]},"effects":[],"duration":0.01,"type":"transition","name":"none","objectID":"0"}],"automaticPlay":false,"hyperlinks":[],"accessibility":[],"baseLayer":{"animations":[],"initialState":{"affineTransform":[1,0,0,1,0,0],"masksToBounds":true,"rotation":0,"scale":1,"position":{"pointX":320,"pointY":568},"width":640,"sublayerTransform":[1,0,0,0,0,1,0,0,0,0,1,0,0,0,0,1],"contentsRect":{"y":0,"x":0,"width":1,"height":1},"opacity":1,"edgeAntialiasingMask":0,"height":1136,"hidden":false,"anchorPoint":{"pointX":0.5,"pointY":0.5}},"objectID":"0","layers":[{"animations":[],"initialState":{"affineTransform":[1,0,0,1,0,0],"masksToBounds":false,"rotation":0,"scale":1,"position":{"pointX":320,"pointY":568},"width":640,"sublayerTransform":[1,0,0,0,0,1,0,0,0,0,1,-0.0005907585228768447,0,0,0,1],"contentsRect":{"y":0,"x":0,"width":1,"height":1},"opacity":1,"edgeAntialiasingMask":15,"height":1136,"hidden":false,"anchorPoint":{"pointX":0.5,"pointY":0.5}},"layers":[{"animations":[],"layers":[],"initialState":{"affineTransform":[1,0,0,1,0,0],"masksToBounds":false,"rotation":0,"scale":1,"position":{"pointX":320,"pointY":568},"width":640,"sublayerTransform":[1,0,0,0,0,1,0,0,0,0,1,0,0,0,0,1],"contentsRect":{"y":0,"x":0,"width":1,"height":1},"opacity":1,"edgeAntialiasingMask":0,"height":1136,"hidden":false,"anchorPoint":{"pointX":0.5,"pointY":0.5}},"texture":"AAF1CC47F60B5C2D43150347C2A117E5"}]}]}}},"targetRectangle":{"y":0.9167579412460327,"x":-4.327822685241699,"width":134.109103679657,"height":77.85036563873291}},{"url":"?slideid=476578B4-8979-4D0A-9BA5-CF3157675D5D","events":{"476578B4-8979-4D0A-9BA5-CF3157675D5D":{"effects":[{"beginTime":0,"baseLayer":{"animations":[],"initialState":{"affineTransform":[1,0,0,1,0,0],"masksToBounds":true,"rotation":0,"scale":1,"position":{"pointX":320,"pointY":568},"width":640,"sublayerTransform":[1,0,0,0,0,1,0,0,0,0,1,0,0,0,0,1],"contentsRect":{"y":0,"x":0,"width":1,"height":1},"opacity":1,"edgeAntialiasingMask":0,"height":1136,"hidden":false,"anchorPoint":{"pointX":0.5,"pointY":0.5}},"objectID":"0","layers":[{"animations":[],"initialState":{"affineTransform":[1,0,0,1,0,0],"masksToBounds":false,"rotation":0,"scale":1,"position":{"pointX":320,"pointY":568},"width":640,"sublayerTransform":[1,0,0,0,0,1,0,0,0,0,1,-0.0005907585228768447,0,0,0,1],"contentsRect":{"y":0,"x":0,"width":1,"height":1},"opacity":1,"edgeAntialiasingMask":15,"height":1136,"hidden":false,"anchorPoint":{"pointX":0.5,"pointY":0.5}},"layers":[{"animations":[],"layers":[],"initialState":{"affineTransform":[1,0,0,1,0,0],"masksToBounds":false,"rotation":0,"scale":1,"position":{"pointX":320,"pointY":568},"width":640,"sublayerTransform":[1,0,0,0,0,1,0,0,0,0,1,0,0,0,0,1],"contentsRect":{"y":0,"x":0,"width":1,"height":1},"opacity":1,"edgeAntialiasingMask":0,"height":1136,"hidden":false,"anchorPoint":{"pointX":0.5,"pointY":0.5}},"texture":"2FCE521D6A14D1F4D863CA0218998B63"},{"animations":[{"from":{"scalar":false},"beginTime":0,"repeatCount":0,"fillMode":"both","property":"hidden","duration":0.01,"to":{"scalar":true}}],"layers":[],"initialState":{"affineTransform":[1,0,0,1,0,0],"masksToBounds":false,"rotation":0,"scale":1,"position":{"pointX":320,"pointY":568},"width":640,"sublayerTransform":[1,0,0,0,0,1,0,0,0,0,1,0,0,0,0,1],"contentsRect":{"y":0,"x":0,"width":1,"height":1},"opacity":1,"edgeAntialiasingMask":0,"height":1136,"hidden":false,"anchorPoint":{"pointX":0.5,"pointY":0.5}},"texture":"AAF1CC47F60B5C2D43150347C2A117E5"}]}]},"effects":[],"duration":0.01,"type":"transition","name":"none","objectID":"0"}],"automaticPlay":false,"hyperlinks":[],"accessibility":[],"baseLayer":{"animations":[],"initialState":{"affineTransform":[1,0,0,1,0,0],"masksToBounds":true,"rotation":0,"scale":1,"position":{"pointX":320,"pointY":568},"width":640,"sublayerTransform":[1,0,0,0,0,1,0,0,0,0,1,0,0,0,0,1],"contentsRect":{"y":0,"x":0,"width":1,"height":1},"opacity":1,"edgeAntialiasingMask":0,"height":1136,"hidden":false,"anchorPoint":{"pointX":0.5,"pointY":0.5}},"objectID":"0","layers":[{"animations":[],"initialState":{"affineTransform":[1,0,0,1,0,0],"masksToBounds":false,"rotation":0,"scale":1,"position":{"pointX":320,"pointY":568},"width":640,"sublayerTransform":[1,0,0,0,0,1,0,0,0,0,1,-0.0005907585228768447,0,0,0,1],"contentsRect":{"y":0,"x":0,"width":1,"height":1},"opacity":1,"edgeAntialiasingMask":15,"height":1136,"hidden":false,"anchorPoint":{"pointX":0.5,"pointY":0.5}},"layers":[{"animations":[],"layers":[],"initialState":{"affineTransform":[1,0,0,1,0,0],"masksToBounds":false,"rotation":0,"scale":1,"position":{"pointX":320,"pointY":568},"width":640,"sublayerTransform":[1,0,0,0,0,1,0,0,0,0,1,0,0,0,0,1],"contentsRect":{"y":0,"x":0,"width":1,"height":1},"opacity":1,"edgeAntialiasingMask":0,"height":1136,"hidden":false,"anchorPoint":{"pointX":0.5,"pointY":0.5}},"texture":"AAF1CC47F60B5C2D43150347C2A117E5"}]}]}}},"targetRectangle":{"y":657.776123046875,"x":230.0243377685547,"width":179.9513101577759,"height":33.3038330078125}}],"accessibility":[{"text":"pasted-image.pdf","targetRectangle":{"y":1003.508483886719,"x":20.87379837036133,"width":619.5855712890625,"height":139.4250946044922}},{"text":"pasted-image.pdf","targetRectangle":{"y":81.16696929931641,"x":9.166584014892578,"width":637,"height":473.2283020019531}},{"text":"pasted-image.pdf","targetRectangle":{"y":556.7951049804688,"x":25.66658401489258,"width":610,"height":199.3571014404297}},{"text":"pasted-image.pdf","targetRectangle":{"y":758.40185546875,"x":24.17236137390137,"width":613.988525390625,"height":239.8569946289062}},{"text":"pasted-image.pdf","targetRectangle":{"y":-3,"x":0,"width":640,"height":1102}},{"text":"pasted-image.pdf","targetRectangle":{"y":-3,"x":0,"width":640,"height":1102}},{"text":"My Bet Builder ","targetRectangle":{"y":20.84808349609375,"x":128.5,"width":165.6479998658896,"height":28.3038330078125}},{"text":"My Bet Builder ","targetRectangle":{"y":14.50762152671814,"x":140.5,"width":217.2449998044223,"height":40.98475646972656}},{"text":"pasted-image.pdf","targetRectangle":{"y":75.66666412353516,"x":-1.562530517578125,"width":643.1250610351562,"height":1060.828125}},{"text":"pasted-image.pdf","targetRectangle":{"y":141,"x":0,"width":20,"height":1026}}],"baseLayer":{"animations":[],"initialState":{"affineTransform":[1,0,0,1,0,0],"masksToBounds":true,"rotation":0,"scale":1,"position":{"pointX":320,"pointY":568},"width":640,"sublayerTransform":[1,0,0,0,0,1,0,0,0,0,1,0,0,0,0,1],"contentsRect":{"y":0,"x":0,"width":1,"height":1},"opacity":1,"edgeAntialiasingMask":0,"height":1136,"hidden":false,"anchorPoint":{"pointX":0.5,"pointY":0.5}},"objectID":"0","layers":[{"animations":[],"initialState":{"affineTransform":[1,0,0,1,0,0],"masksToBounds":false,"rotation":0,"scale":1,"position":{"pointX":320,"pointY":568},"width":640,"sublayerTransform":[1,0,0,0,0,1,0,0,0,0,1,-0.0005907585228768447,0,0,0,1],"contentsRect":{"y":0,"x":0,"width":1,"height":1},"opacity":1,"edgeAntialiasingMask":15,"height":1136,"hidden":false,"anchorPoint":{"pointX":0.5,"pointY":0.5}},"layers":[{"animations":[],"layers":[],"initialState":{"affineTransform":[1,0,0,1,0,0],"masksToBounds":false,"rotation":0,"scale":1,"position":{"pointX":320,"pointY":568},"width":640,"sublayerTransform":[1,0,0,0,0,1,0,0,0,0,1,0,0,0,0,1],"contentsRect":{"y":0,"x":0,"width":1,"height":1},"opacity":1,"edgeAntialiasingMask":0,"height":1136,"hidden":false,"anchorPoint":{"pointX":0.5,"pointY":0.5}},"texture":"AAF1CC47F60B5C2D43150347C2A117E5"}]}]}}]}